ai_assist/__init__.py
ai_assist/ai.py
ai_assist-0.0.2.dist-info/METADATA
ai_assist-0.0.2.dist-info/WHEEL
ai_assist-0.0.2.dist-info/entry_points.txt
ai_assist-0.0.2.dist-info/RECORD
