Metadata-Version: 2.1
Name: ai-assist
Version: 0.0.2
Summary: 
Home-page: https://github.com/czheo/ai-assist
License: GPL-3.0-or-later
Author: czheo
Author-email: 1692400+czheo@users.noreply.github.com
Requires-Python: >=3.10,<4.0
Classifier: License :: OSI Approved :: GNU General Public License v3 or later (GPLv3+)
Classifier: Programming Language :: Python :: 3
Classifier: Programming Language :: Python :: 3.10
Classifier: Programming Language :: Python :: 3.11
Requires-Dist: google-api-python-client (>=2.84.0,<3.0.0)
Requires-Dist: langchain (>=0.0.136,<0.0.137)
Requires-Dist: openai (>=0.27.4,<0.28.0)
Requires-Dist: python-dotenv (>=1.0.0,<2.0.0)
Requires-Dist: termcolor (>=2.3.0,<3.0.0)
Requires-Dist: tiktoken (>=0.3.3,<0.4.0)
Project-URL: Repository, https://github.com/czheo/ai-assist
